detakon/__about__.py
detakon/__init__.py
detakon/detakon.py
detakon-0.0.2.dist-info/METADATA
detakon-0.0.2.dist-info/WHEEL
detakon-0.0.2.dist-info/licenses/LICENSE.txt
detakon-0.0.2.dist-info/RECORD
