Metadata-Version: 2.4
Name: detakon
Version: 0.0.2
Project-URL: Documentation, https://github.com/cknightfury/detakon#readme
Project-URL: Issues, https://github.com/cknightfury/detakon/issues
Project-URL: Source, https://github.com/cknightfury/detakon
Author-email: Clef Knightfury <clef@knightfury.org>
License-Expression: MIT
License-File: LICENSE.txt
Classifier: Development Status :: 4 - Beta
Classifier: Programming Language :: Python
Classifier: Programming Language :: Python :: 3.8
Classifier: Programming Language :: Python :: 3.9
Classifier: Programming Language :: Python :: 3.10
Classifier: Programming Language :: Python :: 3.11
Classifier: Programming Language :: Python :: 3.12
Classifier: Programming Language :: Python :: Implementation :: CPython
Classifier: Programming Language :: Python :: Implementation :: PyPy
Requires-Python: >=3.8
